fedml_dsp/__init__.py
fedml_dsp/dbconnection.py
fedml_dsp/fedml.py
fedml_dsp/logger.py
fedml_dsp-1.0.0.dist-info/METADATA
fedml_dsp-1.0.0.dist-info/WHEEL
fedml_dsp-1.0.0.dist-info/top_level.txt
fedml_dsp-1.0.0.dist-info/RECORD
