Metadata-Version: 2.1
Name: fedml_dsp
Version: 1.0.0
Summary: A python library for building machine learning models on gpu AI Platforms using a federated data source
Author: SAP SE
License: Apache License 2.0
Classifier: Programming Language :: Python :: 3
Classifier: Operating System :: OS Independent
Requires-Python: >=3
Requires-Dist: hdbcli
Requires-Dist: numpy ==1.23.0
Requires-Dist: pandas <1.6.0dev0,>=1.3
Requires-Dist: pyspark
Requires-Dist: ai-core-sdk
Requires-Dist: pyyaml
Requires-Dist: requests
Requires-Dist: pyarrow <15
Requires-Dist: torch
